enviroMS/__init__.py
enviroMS/cli.py
enviroMS/diWorkflow.py
enviroMS/singleMzSearch.py
EnviroMS-4.1.3.dist-info/LICENSE
EnviroMS-4.1.3.dist-info/METADATA
EnviroMS-4.1.3.dist-info/WHEEL
EnviroMS-4.1.3.dist-info/entry_points.txt
EnviroMS-4.1.3.dist-info/top_level.txt
EnviroMS-4.1.3.dist-info/RECORD
