Metadata-Version: 2.1
Name: EnviroMS
Version: 4.1.3
Summary: Search and Assign Molecular Formulas for Complex Mixtures of Small Molecules
Home-page: https://github.com/EMSL-Computing/EnviroMS
Author: Corilo, Yuri
Author-email: corilo@pnnl.gov
License: GNU Affero General Public License v3.0
Platform: UNKNOWN
Classifier: License :: OSI Approved :: BSD License
Classifier: Programming Language :: Python :: 3.6
Classifier: Programming Language :: Python :: 3.7
Requires-Dist: Click
Requires-Dist: tabulate
Requires-Dist: CoreMS
Requires-Dist: requests
